SPI_BIST.v
module BIST(
    input wire clk,
    //input wire in_data,
     input wire reset, 

    output wire S_cs, 
    output wire  S_s_clk,
    output wire[7:0] data_out,
    output wire [3:0] counter,
    output wire [2:0] Code,
    output wire [7:0] L_data
);
//wire [7:0] L_data;

LFSR V0(clk, reset, L_data);
spi_master V1 (L_data,reset, clk, S_cs, S_s_clk, data_out, counter);
Cmp V2 (S_s_clk, L_data, data_out, Code);



endmodule






module LFSR(
    input wire clk,
    input wire reset,
    output wire[7:0] data_out
);
reg [7:0] out = 8'h00;
reg [2:0] count=3'd7;
wire w_xor;
assign w_xor = out[7] ^ out[1];

always @(posedge clk)
begin
    if(reset)
        begin
            out <= 8'h10;
        end
    else
   // while (count>=0) 
     //   begin
       //   out[count]<= out[count-1];
         // count <= count-1;
         // if(count==0)
          //  out[count] <= w_xor; 
        //end 
        
        
        out <= {out[6],out[5],out[4],out[3],out[2],out[1],out[0],w_xor}; 
        #42;
end
assign data_out = out;

endmodule
//SPI Module

module spi_master(

    input wire [7:0] in_data,
    input wire reset,
    input wire clk,        //system clock
    //input reset_n;
    //input go;

    output wire S_cs, 
    output wire  S_s_clk,
    output wire  [7:0] data_out,
    output wire [3:0] counter
    
);

//reg BIST_MODE = 0;
//reg GO;
reg [7:0] MOSI;   //shift register
reg cs;            // control chip select   when cs is low(i.e., 0)it transfers data to that slave
reg s_clk;          // spi clock
reg [1:0] state;
reg [3:0] count;

//for normal mode and BIST mode....if BIST MODE==1 then BIST mode is on
//always @(reset_n) 
//begin
    //if(reset_n==1)
     //   BIST_MODE = 1;
   // else 
  //      BIST_MODE = 0;
    
//end

//always @(go) 
//begin
 //   if(go==1)

    
//end 

always @(posedge clk or posedge reset) 
begin
    if(reset)
        begin
            MOSI <= 8'b0;
            count <= 4'd0;
            cs <= 1'b1;
            s_clk <= 1'b0;
        end
      
else 
    begin
      case(state)
        0: begin
          s_clk <= 1'b0;
          cs <=1'b1;
          state <=1;
        end

        1: begin
          s_clk <= 1'b0;
          cs <= 1'b0;
          MOSI <= {MOSI[6:0],in_data};
          count <= count-1;
          state <=2;
        end 

        2:begin
          s_clk <=1'b1;
            if (count>0)
                state <= 1;
            else begin
                count <= 8;
                state <=0;
                end
        end
        default :state <=0; 
      endcase
end
end
assign S_cs = cs;
assign S_s_clk = s_clk;
assign data_out = MOSI;
assign counter = count;

endmodule   

module Cmp(
    input wire clk,
    input wire [7:0] L_data,
    input wire [7:0] S_data,

    output wire [2:0] Code
);

reg [2:0] code;

always @(negedge clk)
    begin
      if(L_data == S_data)
             code = 3'b101;
        else
             code = 3'b001;
    end

    assign Code = code;

endmodule

SPI_BIST_TB.v

`include "SPI_BIST.v"

module BIST_tb;

    reg clk;
    reg reset; 

    wire S_cs; 
    wire S_s_clk;
    wire[7:0] data_out;
    wire [3:0] counter;
    wire [2:0] Code;
    wire [7:0] L_data;

BIST dut(
  .clk(clk),
  .reset(reset),
  .S_cs(S_cs),
  .S_s_clk(S_s_clk),
  .data_out(data_out),
  .counter(counter),
  .Code(Code),
  .L_data(L_data)
);

initial 
  begin
  clk = 0;
  reset = 1;
end

always #10 clk= ~clk;

  initial
   begin
     $dumpfile("output2.vcd");
     $dumpvars;
   end
  
initial begin
   #20 reset =1'b0;
  
end
initial begin
  #1000 $finish;
end

endmodule

output2.vcd
$date
	Sun Jul 31 14:02:42 2022
$end
$version
	Icarus Verilog
$end
$timescale
	1s
$end
$scope module BIST_tb $end
$var wire 8 ! data_out [7:0] $end
$var wire 4 " counter [3:0] $end
$var wire 1 # S_s_clk $end
$var wire 1 $ S_cs $end
$var wire 8 % L_data [7:0] $end
$var wire 3 & Code [2:0] $end
$var reg 1 ' clk $end
$var reg 1 ( reset $end
$scope module dut $end
$var wire 1 ' clk $end
$var wire 1 ( reset $end
$var wire 8 ) data_out [7:0] $end
$var wire 4 * counter [3:0] $end
$var wire 1 # S_s_clk $end
$var wire 1 $ S_cs $end
$var wire 8 + L_data [7:0] $end
$var wire 3 , Code [2:0] $end
$scope module V0 $end
$var wire 1 ' clk $end
$var wire 8 - data_out [7:0] $end
$var wire 1 ( reset $end
$var wire 1 . w_xor $end
$var reg 3 / count [2:0] $end
$var reg 8 0 out [7:0] $end
$upscope $end
$scope module V1 $end
$var wire 1 $ S_cs $end
$var wire 1 # S_s_clk $end
$var wire 1 ' clk $end
$var wire 4 1 counter [3:0] $end
$var wire 8 2 data_out [7:0] $end
$var wire 8 3 in_data [7:0] $end
$var wire 1 ( reset $end
$var reg 8 4 MOSI [7:0] $end
$var reg 4 5 count [3:0] $end
$var reg 1 6 cs $end
$var reg 1 7 s_clk $end
$var reg 2 8 state [1:0] $end
$upscope $end
$scope module V2 $end
$var wire 3 9 Code [2:0] $end
$var wire 8 : L_data [7:0] $end
$var wire 8 ; S_data [7:0] $end
$var wire 1 # clk $end
$var reg 3 < code [2:0] $end
$upscope $end
$upscope $end
$upscope $end
$enddefinitions $end
#0
$dumpvars
b101 <
b0 ;
b0 :
b101 9
bx 8
07
16
b0 5
b0 4
b0 3
b0 2
b0 1
b0 0
b111 /
0.
b0 -
b101 ,
b0 +
b0 *
b0 )
1(
0'
b101 &
b0 %
1$
0#
b0 "
b0 !
$end
#10
b10000 %
b10000 +
b10000 -
b10000 3
b10000 :
b10000 0
1'
#20
0'
0(
#30
b0 8
1'
#40
0'
#50
b1 8
1'
#60
0'
#70
b100000 %
b100000 +
b100000 -
b100000 3
b100000 :
b100000 0
b10 8
b1111 "
b1111 *
b1111 1
b1111 5
b10000 !
b10000 )
b10000 2
b10000 ;
b10000 4
0$
06
1'
#80
0'
#90
b1 8
1#
17
1'
#100
0'
#110
b10 8
b1110 "
b1110 *
b1110 1
b1110 5
b100000 !
b100000 )
b100000 2
b100000 ;
b100000 4
0#
07
1'
#120
0'
#130
b1000000 %
b1000000 +
b1000000 -
b1000000 3
b1000000 :
b1000000 0
b1 8
1#
17
1'
#140
0'
#150
b10 8
b1101 "
b1101 *
b1101 1
b1101 5
b1000000 !
b1000000 )
b1000000 2
b1000000 ;
b1000000 4
0#
07
1'
#160
0'
#170
b1 8
1#
17
1'
#180
0'
#190
1.
b1 &
b1 ,
b1 9
b1 <
b10000000 %
b10000000 +
b10000000 -
b10000000 3
b10000000 :
b10000000 0
b10 8
b1100 "
b1100 *
b1100 1
b1100 5
0#
07
1'
#200
0'
#210
b1 8
1#
17
1'
#220
0'
#230
b101 &
b101 ,
b101 9
b101 <
b10 8
b1011 "
b1011 *
b1011 1
b1011 5
b10000000 !
b10000000 )
b10000000 2
b10000000 ;
b10000000 4
0#
07
1'
#240
0'
#250
0.
b1 %
b1 +
b1 -
b1 3
b1 :
b1 0
b1 8
1#
17
1'
#260
0'
#270
b10 8
b1010 "
b1010 *
b1010 1
b1010 5
b1 !
b1 )
b1 2
b1 ;
b1 4
0#
07
1'
#280
0'
#290
b1 8
1#
17
1'
#300
0'
#310
1.
b1 &
b1 ,
b1 9
b1 <
b10 %
b10 +
b10 -
b10 3
b10 :
b10 0
b10 8
b1001 "
b1001 *
b1001 1
b1001 5
0#
07
1'
#320
0'
#330
b1 8
1#
17
1'
#340
0'
#350
b101 &
b101 ,
b101 9
b101 <
b10 8
b1000 "
b1000 *
b1000 1
b1000 5
b10 !
b10 )
b10 2
b10 ;
b10 4
0#
07
1'
#360
0'
#370
0.
b101 %
b101 +
b101 -
b101 3
b101 :
b101 0
b1 8
1#
17
1'
#380
0'
#390
b10 8
b111 "
b111 *
b111 1
b111 5
b101 !
b101 )
b101 2
b101 ;
b101 4
0#
07
1'
#400
0'
#410
b1 8
1#
17
1'
#420
0'
#430
1.
b1 &
b1 ,
b1 9
b1 <
b1010 %
b1010 +
b1010 -
b1010 3
b1010 :
b1010 0
b10 8
b110 "
b110 *
b110 1
b110 5
0#
07
1'
#440
0'
#450
b1 8
1#
17
1'
#460
0'
#470
b101 &
b101 ,
b101 9
b101 <
b10 8
b101 "
b101 *
b101 1
b101 5
b1010 !
b1010 )
b1010 2
b1010 ;
b1010 4
0#
07
1'
#480
0'
#490
0.
b10101 %
b10101 +
b10101 -
b10101 3
b10101 :
b10101 0
b1 8
1#
17
1'
#500
0'
#510
b10 8
b100 "
b100 *
b100 1
b100 5
b10101 !
b10101 )
b10101 2
b10101 ;
b10101 4
0#
07
1'
#520
0'
#530
b1 8
1#
17
1'
#540
0'
#550
1.
b1 &
b1 ,
b1 9
b1 <
b101010 %
b101010 +
b101010 -
b101010 3
b101010 :
b101010 0
b10 8
b11 "
b11 *
b11 1
b11 5
0#
07
1'
#560
0'
#570
b1 8
1#
17
1'
#580
0'
#590
b101 &
b101 ,
b101 9
b101 <
b10 8
b10 "
b10 *
b10 1
b10 5
b101010 !
b101010 )
b101010 2
b101010 ;
b101010 4
0#
07
1'
#600
0'
#610
0.
b1010101 %
b1010101 +
b1010101 -
b1010101 3
b1010101 :
b1010101 0
b1 8
1#
17
1'
#620
0'
#630
b10 8
b1 "
b1 *
b1 1
b1 5
b1010101 !
b1010101 )
b1010101 2
b1010101 ;
b1010101 4
0#
07
1'
#640
0'
#650
b1 8
1#
17
1'
#660
0'
#670
b1 &
b1 ,
b1 9
b1 <
b10101010 %
b10101010 +
b10101010 -
b10101010 3
b10101010 :
b10101010 0
b10 8
b0 "
b0 *
b0 1
b0 5
0#
07
1'
#680
0'
#690
b0 8
b1000 "
b1000 *
b1000 1
b1000 5
1#
17
1'
#700
0'
#710
b1 8
1$
16
0#
07
1'
#720
0'
#730
b1010100 %
b1010100 +
b1010100 -
b1010100 3
b1010100 :
b1010100 0
b10 8
b111 "
b111 *
b111 1
b111 5
b10101010 !
b10101010 )
b10101010 2
b10101010 ;
b10101010 4
0$
06
1'
#740
0'
#750
b1 8
1#
17
1'
#760
0'
#770
b101 &
b101 ,
b101 9
b101 <
b10 8
b110 "
b110 *
b110 1
b110 5
b1010100 !
b1010100 )
b1010100 2
b1010100 ;
b1010100 4
0#
07
1'
#780
0'
#790
1.
b10101000 %
b10101000 +
b10101000 -
b10101000 3
b10101000 :
b10101000 0
b1 8
1#
17
1'
#800
0'
#810
b10 8
b101 "
b101 *
b101 1
b101 5
b10101000 !
b10101000 )
b10101000 2
b10101000 ;
b10101000 4
0#
07
1'
#820
0'
#830
b1 8
1#
17
1'
#840
0'
#850
0.
b1 &
b1 ,
b1 9
b1 <
b1010001 %
b1010001 +
b1010001 -
b1010001 3
b1010001 :
b1010001 0
b10 8
b100 "
b100 *
b100 1
b100 5
0#
07
1'
#860
0'
#870
b1 8
1#
17
1'
#880
0'
#890
b101 &
b101 ,
b101 9
b101 <
b10 8
b11 "
b11 *
b11 1
b11 5
b1010001 !
b1010001 )
b1010001 2
b1010001 ;
b1010001 4
0#
07
1'
#900
0'
#910
b10100010 %
b10100010 +
b10100010 -
b10100010 3
b10100010 :
b10100010 0
b1 8
1#
17
1'
#920
0'
#930
b10 8
b10 "
b10 *
b10 1
b10 5
b10100010 !
b10100010 )
b10100010 2
b10100010 ;
b10100010 4
0#
07
1'
#940
0'
#950
b1 8
1#
17
1'
#960
0'
#970
b1 &
b1 ,
b1 9
b1 <
b1000100 %
b1000100 +
b1000100 -
b1000100 3
b1000100 :
b1000100 0
b10 8
b1 "
b1 *
b1 1
b1 5
0#
07
1'
#980
0'
#990
b1 8
1#
17
1'
